README
setup.py
pypi2pkgsys/__init__.py
pypi2pkgsys/dump.py
pypi2pkgsys/package_system.py
pypi2pkgsys/pypi2packages.py
pypi2pkgsys/pypi_objects.py
pypi2pkgsys/pypi_utils.py
pypi2pkgsys/utils.py
pypi2pkgsys.egg-info/PKG-INFO
pypi2pkgsys.egg-info/SOURCES.txt
pypi2pkgsys.egg-info/dependency_links.txt
pypi2pkgsys.egg-info/entry_points.txt
pypi2pkgsys.egg-info/not-zip-safe
pypi2pkgsys.egg-info/requires.txt
pypi2pkgsys.egg-info/top_level.txt
pypi2pkgsys/patches/Cheetah-1.0-use-setuptools.patch
pypi2pkgsys/patches/Cheetah-2.0.1-use-setuptools.patch
pypi2pkgsys/patches/CocoPy-1.1.0rc-fix-structure.patch
pypi2pkgsys/patches/broken.txt
pypi2pkgsys/patches/fakemail-python-1.0beta-setuptools.patch
pypi2pkgsys/patches/htmltotext-0.7.2-fixsetup.patch
pypi2pkgsys/patches/index.ini
pypi2pkgsys/patches/infrae.subversion-1.3.1-fixsetup.patch
pypi2pkgsys/patches/pypi2pkgsys.log
pypi2pkgsys/patches/setuptools-0.6_rc7-noexe.patch
pypi2pkgsys/patches/setuptools-0.6_rc8-downloadopt.patch
pypi2pkgsys/patches/setuptools-0.6_rc8-svn-1.5.patch
pypi2pkgsys/portage/__init__.py
pypi2pkgsys/portage/setup.py.tmpl
pypi2pkgsys/portage/single.py.tmpl
pypi2pkgsys/portage/utils.py
scripts/pypi-logstats.py
scripts/pypi-manualcache.py
scripts/pypi2dpkg
scripts/pypi2portage
scripts/pypi2rpm