Metadata-Version: 1.0
Name: pypi2pkgsys
Version: 0.0.6
Summary: Generate package files(gentoo ebuild) from PyPI index.
Home-page: http://code.google.com/p/pypi2pkgsys/
Author: Charles Wang
Author-email: charlesw123456@gmail.com
License: BSD
Keywords: PyPI distutils setuptools package management
Platform: UNKNOWN
Classifier: Development Status :: 3 - Alpha
Classifier: Intended Audience :: System Administrators
Classifier: License :: OSI Approved :: BSD License
Classifier: Operating System :: OS Independent
Classifier: Programming Language :: Python
Classifier: Topic :: System :: Archiving :: Packaging
Classifier: Topic :: System :: Systems Administration
Classifier: Topic :: Utilities
